<annotation>
	<folder>singleGrid</folder>
	<filename>61.jpg</filename>
	<path>C:\Users\bobar\Documents\GitHub\Database\reduced\singleGrid\61.jpg</path>
	<source>
		<database>Unknown</database>
	</source>
	<size>
		<width>960</width>
		<height>540</height>
		<depth>3</depth>
	</size>
	<segmented>0</segmented>
	<object>
		<name>poop</name>
		<pose>Unspecified</pose>
		<truncated>1</truncated>
		<difficult>0</difficult>
		<bndbox>
			<xmin>362</xmin>
			<ymin>1</ymin>
			<xmax>421</xmax>
			<ymax>36</ymax>
		</bndbox>
	</object>
</annotation>
