<annotation>
	<folder>trippleGrass</folder>
	<filename>215.jpg</filename>
	<path>/Users/becerrilblas/Github/Database/reduced/all/images/trippleGrass/215.jpg</path>
	<source>
		<database>Unknown</database>
	</source>
	<size>
		<width>960</width>
		<height>540</height>
		<depth>3</depth>
	</size>
	<segmented>0</segmented>
	<object>
		<name>poop</name>
		<pose>Unspecified</pose>
		<truncated>0</truncated>
		<difficult>0</difficult>
		<bndbox>
			<xmin>192</xmin>
			<ymin>256</ymin>
			<xmax>311</xmax>
			<ymax>361</ymax>
		</bndbox>
	</object>
	<object>
		<name>poop</name>
		<pose>Unspecified</pose>
		<truncated>0</truncated>
		<difficult>0</difficult>
		<bndbox>
			<xmin>408</xmin>
			<ymin>204</ymin>
			<xmax>510</xmax>
			<ymax>290</ymax>
		</bndbox>
	</object>
	<object>
		<name>poop</name>
		<pose>Unspecified</pose>
		<truncated>0</truncated>
		<difficult>0</difficult>
		<bndbox>
			<xmin>558</xmin>
			<ymin>273</ymin>
			<xmax>688</xmax>
			<ymax>389</ymax>
		</bndbox>
	</object>
</annotation>
