<annotation>
	<folder>trippleGrass</folder>
	<filename>384.jpg</filename>
	<path>C:\Users\bobar\Documents\GitHub\Database\reduced\all\images\trippleGrass\384.jpg</path>
	<source>
		<database>Unknown</database>
	</source>
	<size>
		<width>960</width>
		<height>540</height>
		<depth>3</depth>
	</size>
	<segmented>0</segmented>
	<object>
		<name>poop</name>
		<pose>Unspecified</pose>
		<truncated>0</truncated>
		<difficult>0</difficult>
		<bndbox>
			<xmin>488</xmin>
			<ymin>69</ymin>
			<xmax>578</xmax>
			<ymax>140</ymax>
		</bndbox>
	</object>
	<object>
		<name>poop</name>
		<pose>Unspecified</pose>
		<truncated>0</truncated>
		<difficult>0</difficult>
		<bndbox>
			<xmin>139</xmin>
			<ymin>284</ymin>
			<xmax>255</xmax>
			<ymax>386</ymax>
		</bndbox>
	</object>
	<object>
		<name>poop</name>
		<pose>Unspecified</pose>
		<truncated>1</truncated>
		<difficult>0</difficult>
		<bndbox>
			<xmin>878</xmin>
			<ymin>365</ymin>
			<xmax>960</xmax>
			<ymax>458</ymax>
		</bndbox>
	</object>
</annotation>
