<annotation>
	<folder>trippleRocks2</folder>
	<filename>trtwo192.jpg</filename>
	<path>D:\Database\reduced\all\images\trippleRocks2\trtwo192.jpg</path>
	<source>
		<database>Unknown</database>
	</source>
	<size>
		<width>960</width>
		<height>540</height>
		<depth>3</depth>
	</size>
	<segmented>0</segmented>
	<object>
		<name>poop</name>
		<pose>Unspecified</pose>
		<truncated>0</truncated>
		<difficult>0</difficult>
		<bndbox>
			<xmin>563</xmin>
			<ymin>11</ymin>
			<xmax>632</xmax>
			<ymax>82</ymax>
		</bndbox>
	</object>
	<object>
		<name>poop</name>
		<pose>Unspecified</pose>
		<truncated>0</truncated>
		<difficult>0</difficult>
		<bndbox>
			<xmin>678</xmin>
			<ymin>175</ymin>
			<xmax>794</xmax>
			<ymax>253</ymax>
		</bndbox>
	</object>
	<object>
		<name>poop</name>
		<pose>Unspecified</pose>
		<truncated>0</truncated>
		<difficult>0</difficult>
		<bndbox>
			<xmin>773</xmin>
			<ymin>338</ymin>
			<xmax>895</xmax>
			<ymax>455</ymax>
		</bndbox>
	</object>
</annotation>
