<annotation>
	<folder>tripple</folder>
	<filename>66.jpg</filename>
	<path>C:\Users\bobar\Documents\GitHub\Database\reduced\tripple\66.jpg</path>
	<source>
		<database>Unknown</database>
	</source>
	<size>
		<width>960</width>
		<height>540</height>
		<depth>3</depth>
	</size>
	<segmented>0</segmented>
	<object>
		<name>poop</name>
		<pose>Unspecified</pose>
		<truncated>0</truncated>
		<difficult>0</difficult>
		<bndbox>
			<xmin>559</xmin>
			<ymin>357</ymin>
			<xmax>663</xmax>
			<ymax>465</ymax>
		</bndbox>
	</object>
	<object>
		<name>poop</name>
		<pose>Unspecified</pose>
		<truncated>0</truncated>
		<difficult>0</difficult>
		<bndbox>
			<xmin>785</xmin>
			<ymin>208</ymin>
			<xmax>877</xmax>
			<ymax>293</ymax>
		</bndbox>
	</object>
	<object>
		<name>poop</name>
		<pose>Unspecified</pose>
		<truncated>1</truncated>
		<difficult>0</difficult>
		<bndbox>
			<xmin>888</xmin>
			<ymin>86</ymin>
			<xmax>960</xmax>
			<ymax>168</ymax>
		</bndbox>
	</object>
</annotation>
