<annotation>
	<folder>trippleGrass</folder>
	<filename>187.jpg</filename>
	<path>/Users/becerrilblas/Github/Database/reduced/all/images/trippleGrass/187.jpg</path>
	<source>
		<database>Unknown</database>
	</source>
	<size>
		<width>960</width>
		<height>540</height>
		<depth>3</depth>
	</size>
	<segmented>0</segmented>
	<object>
		<name>poop</name>
		<pose>Unspecified</pose>
		<truncated>0</truncated>
		<difficult>0</difficult>
		<bndbox>
			<xmin>291</xmin>
			<ymin>242</ymin>
			<xmax>416</xmax>
			<ymax>343</ymax>
		</bndbox>
	</object>
	<object>
		<name>poop</name>
		<pose>Unspecified</pose>
		<truncated>0</truncated>
		<difficult>0</difficult>
		<bndbox>
			<xmin>419</xmin>
			<ymin>143</ymin>
			<xmax>521</xmax>
			<ymax>229</ymax>
		</bndbox>
	</object>
	<object>
		<name>poop</name>
		<pose>Unspecified</pose>
		<truncated>0</truncated>
		<difficult>0</difficult>
		<bndbox>
			<xmin>608</xmin>
			<ymin>168</ymin>
			<xmax>707</xmax>
			<ymax>254</ymax>
		</bndbox>
	</object>
</annotation>
