<annotation>
	<folder>ropePoop2</folder>
	<filename>rptwo61.jpg</filename>
	<path>D:\Database\reduced\all\images\ropePoop2\rptwo61.jpg</path>
	<source>
		<database>Unknown</database>
	</source>
	<size>
		<width>960</width>
		<height>540</height>
		<depth>3</depth>
	</size>
	<segmented>0</segmented>
	<object>
		<name>poop</name>
		<pose>Unspecified</pose>
		<truncated>0</truncated>
		<difficult>0</difficult>
		<bndbox>
			<xmin>66</xmin>
			<ymin>182</ymin>
			<xmax>197</xmax>
			<ymax>281</ymax>
		</bndbox>
	</object>
	<object>
		<name>poop</name>
		<pose>Unspecified</pose>
		<truncated>0</truncated>
		<difficult>0</difficult>
		<bndbox>
			<xmin>185</xmin>
			<ymin>339</ymin>
			<xmax>318</xmax>
			<ymax>458</ymax>
		</bndbox>
	</object>
	<object>
		<name>poop</name>
		<pose>Unspecified</pose>
		<truncated>0</truncated>
		<difficult>0</difficult>
		<bndbox>
			<xmin>407</xmin>
			<ymin>90</ymin>
			<xmax>487</xmax>
			<ymax>169</ymax>
		</bndbox>
	</object>
	<object>
		<name>poop</name>
		<pose>Unspecified</pose>
		<truncated>0</truncated>
		<difficult>0</difficult>
		<bndbox>
			<xmin>561</xmin>
			<ymin>238</ymin>
			<xmax>652</xmax>
			<ymax>331</ymax>
		</bndbox>
	</object>
	<object>
		<name>poop</name>
		<pose>Unspecified</pose>
		<truncated>0</truncated>
		<difficult>0</difficult>
		<bndbox>
			<xmin>802</xmin>
			<ymin>101</ymin>
			<xmax>916</xmax>
			<ymax>202</ymax>
		</bndbox>
	</object>
	<object>
		<name>poop</name>
		<pose>Unspecified</pose>
		<truncated>1</truncated>
		<difficult>0</difficult>
		<bndbox>
			<xmin>845</xmin>
			<ymin>287</ymin>
			<xmax>960</xmax>
			<ymax>402</ymax>
		</bndbox>
	</object>
</annotation>
