<annotation><filename>CardsDataset_2019_8_18_519692_wlbs.jpg</filename><origin>D:\Database\scripts\testing_cards\images\train\image\IMG_2615.jpg</origin><path>D:\Database\scripts\testing_cards\reducedImages\train\CardsDataset_2019_8_18_519692_wlbs.jpg</path><source><database>CardsDataset</database></source><size><height>300</height><width>300</width><depth>3</depth></size><data_augmentation><type>Unspecified</type></data_augmentation><segmented>0</segmented><object><name>card</name><pose>Unspecified</pose><truncated>0</truncated><difficult>0</difficult><bndbox><xmin>1</xmin><ymin>43</ymin><xmax>97</xmax><ymax>236</ymax></bndbox></object><object><name>card</name><pose>Unspecified</pose><truncated>0</truncated><difficult>0</difficult><bndbox><xmin>105</xmin><ymin>3</ymin><xmax>258</xmax><ymax>156</ymax></bndbox></object></annotation>