<annotation>
	<folder>trippleRocks2</folder>
	<filename>trtwo354.jpg</filename>
	<path>D:\Database\reduced\all\images\trippleRocks2\trtwo354.jpg</path>
	<source>
		<database>Unknown</database>
	</source>
	<size>
		<width>960</width>
		<height>540</height>
		<depth>3</depth>
	</size>
	<segmented>0</segmented>
	<object>
		<name>poop</name>
		<pose>Unspecified</pose>
		<truncated>0</truncated>
		<difficult>0</difficult>
		<bndbox>
			<xmin>787</xmin>
			<ymin>221</ymin>
			<xmax>913</xmax>
			<ymax>329</ymax>
		</bndbox>
	</object>
	<object>
		<name>poop</name>
		<pose>Unspecified</pose>
		<truncated>0</truncated>
		<difficult>0</difficult>
		<bndbox>
			<xmin>824</xmin>
			<ymin>101</ymin>
			<xmax>937</xmax>
			<ymax>187</ymax>
		</bndbox>
	</object>
	<object>
		<name>poop</name>
		<pose>Unspecified</pose>
		<truncated>0</truncated>
		<difficult>0</difficult>
		<bndbox>
			<xmin>589</xmin>
			<ymin>259</ymin>
			<xmax>690</xmax>
			<ymax>352</ymax>
		</bndbox>
	</object>
</annotation>
