<annotation>
	<folder>trippleRocks</folder>
	<filename>tr94.jpg</filename>
	<path>D:\Database\reduced\all\images\trippleRocks\tr94.jpg</path>
	<source>
		<database>Unknown</database>
	</source>
	<size>
		<width>960</width>
		<height>540</height>
		<depth>3</depth>
	</size>
	<segmented>0</segmented>
	<object>
		<name>poop</name>
		<pose>Unspecified</pose>
		<truncated>0</truncated>
		<difficult>0</difficult>
		<bndbox>
			<xmin>533</xmin>
			<ymin>7</ymin>
			<xmax>617</xmax>
			<ymax>75</ymax>
		</bndbox>
	</object>
	<object>
		<name>poop</name>
		<pose>Unspecified</pose>
		<truncated>0</truncated>
		<difficult>0</difficult>
		<bndbox>
			<xmin>673</xmin>
			<ymin>239</ymin>
			<xmax>771</xmax>
			<ymax>331</ymax>
		</bndbox>
	</object>
	<object>
		<name>poop</name>
		<pose>Unspecified</pose>
		<truncated>0</truncated>
		<difficult>0</difficult>
		<bndbox>
			<xmin>182</xmin>
			<ymin>222</ymin>
			<xmax>277</xmax>
			<ymax>306</ymax>
		</bndbox>
	</object>
</annotation>
